gcn/__init__.py
gcn/_version.py
gcn/cmdline.py
gcn/handlers.py
gcn/notice_types.py
gcn/voeventclient.py
gcn/tests/__init__.py
gcn/tests/test_cmdline.py
gcn/tests/test_handlers.py
gcn/tests/test_kill.py
gcn/tests/test_voeventclient.py
gcn/tests/data/__init__.py
gcn/tests/data/gbm_flt_pos.xml
gcn/tests/data/kill_socket.xml
pygcn-1.1.3.dist-info/LICENSE.md
pygcn-1.1.3.dist-info/METADATA
pygcn-1.1.3.dist-info/WHEEL
pygcn-1.1.3.dist-info/entry_points.txt
pygcn-1.1.3.dist-info/top_level.txt
pygcn-1.1.3.dist-info/RECORD
