Metadata-Version: 2.1
Name: pygcn
Version: 1.1.3
Summary: Anonymous VOEvent client for receiving GCN/TAN notices in XML format
Home-page: https://github.com/nasa-gcn/pygcn
Author: Leo Singer
Author-email: leo.singer@ligo.org
License: GPL-2+
Project-URL: Bug Tracker, https://github.com/nasa-gcn/pygcn/issues
Project-URL: Source Code, https://github.com/nasa-gcn/pygcn
Classifier: Development Status :: 5 - Production/Stable
Classifier: Environment :: Console
Classifier: Intended Audience :: Science/Research
Classifier: License :: OSI Approved :: GNU General Public License v3 or later (GPLv3+)
Classifier: Operating System :: POSIX
Classifier: Programming Language :: Python :: 3.7
Classifier: Programming Language :: Python :: 3.8
Classifier: Programming Language :: Python :: 3.9
Classifier: Programming Language :: Python :: 3.10
Classifier: Topic :: Internet
Classifier: Topic :: Scientific/Engineering :: Astronomy
License-File: LICENSE.md
